phasefront/__init__.py
phasefront/_version.py
phasefront/config.py
phasefront/docs.py
phasefront/py.typed
phasefront/ssh.py
phasefront/utils.py
phasefront/docs/PQ strEEm Python doc.pdf
phasefront/docs/site/404.html
phasefront/docs/site/PQ strEEm Python doc.pdf
phasefront/docs/site/custom.css
phasefront/docs/site/development.html
phasefront/docs/site/index.html
phasefront/docs/site/sitemap.xml
phasefront/docs/site/sitemap.xml.gz
phasefront/docs/site/assets/images/favicon.png
phasefront/docs/site/assets/javascripts/bundle.83f73b43.min.js
phasefront/docs/site/assets/javascripts/bundle.83f73b43.min.js.map
phasefront/docs/site/assets/javascripts/lunr/tinyseg.js
phasefront/docs/site/assets/javascripts/lunr/wordcut.js
phasefront/docs/site/assets/javascripts/lunr/min/lunr.ar.min.js
phasefront/docs/site/assets/javascripts/lunr/min/lunr.da.min.js
phasefront/docs/site/assets/javascripts/lunr/min/lunr.de.min.js
phasefront/docs/site/assets/javascripts/lunr/min/lunr.du.min.js
phasefront/docs/site/assets/javascripts/lunr/min/lunr.el.min.js
phasefront/docs/site/assets/javascripts/lunr/min/lunr.es.min.js
phasefront/docs/site/assets/javascripts/lunr/min/lunr.fi.min.js
phasefront/docs/site/assets/javascripts/lunr/min/lunr.fr.min.js
phasefront/docs/site/assets/javascripts/lunr/min/lunr.he.min.js
phasefront/docs/site/assets/javascripts/lunr/min/lunr.hi.min.js
phasefront/docs/site/assets/javascripts/lunr/min/lunr.hu.min.js
phasefront/docs/site/assets/javascripts/lunr/min/lunr.hy.min.js
phasefront/docs/site/assets/javascripts/lunr/min/lunr.it.min.js
phasefront/docs/site/assets/javascripts/lunr/min/lunr.ja.min.js
phasefront/docs/site/assets/javascripts/lunr/min/lunr.jp.min.js
phasefront/docs/site/assets/javascripts/lunr/min/lunr.kn.min.js
phasefront/docs/site/assets/javascripts/lunr/min/lunr.ko.min.js
phasefront/docs/site/assets/javascripts/lunr/min/lunr.multi.min.js
phasefront/docs/site/assets/javascripts/lunr/min/lunr.nl.min.js
phasefront-0.2.5.dist-info/METADATA
phasefront-0.2.5.dist-info/WHEEL
phasefront-0.2.5.dist-info/entry_points.txt
phasefront-0.2.5.dist-info/top_level.txt
phasefront-0.2.5.dist-info/RECORD
