Metadata-Version: 2.1
Name: phasefront
Version: 0.2.5
Summary: PQ strEEm Exploratory Data Analysis tool
Author-email: Kevin Davies <kdavies@phasefront.io>
License: Copyright 2024 PhaseFront and Renewable Edge LLC
Classifier: Development Status :: 4 - Beta
Classifier: Intended Audience :: Science/Research
Classifier: Programming Language :: Python :: 3
Classifier: Programming Language :: Python :: 3.8
Classifier: Programming Language :: Python :: 3.9
Classifier: Programming Language :: Python :: 3.10
Classifier: Programming Language :: Python :: 3.11
Requires-Python: >=3.8
Requires-Dist: iso8601>=2.1
Requires-Dist: matplotlib>=3.8
Requires-Dist: numpy>=1.24
Requires-Dist: paramiko>=3.3
Requires-Dist: pyarrow>=14.0
Requires-Dist: tomli>=2.0
Requires-Dist: tqdm>=4.65.0
